setup.py
rfc/__init__.py
rfc/cli.py
rfc.egg-info/PKG-INFO
rfc.egg-info/SOURCES.txt
rfc.egg-info/dependency_links.txt
rfc.egg-info/entry_points.txt
rfc.egg-info/requires.txt
rfc.egg-info/top_level.txt