Metadata-Version: 1.1
Name: rfc
Version: 0.1.0
Summary: View RFCs in the terminal
Home-page: https://github.com/lewiseason/rfc
Author: Lewis Eason
Author-email: me@lewiseason.co.uk
License: UNKNOWN
Platform: UNKNOWN
Classifier: Programming Language :: Python :: 2.7
Classifier: Programming Language :: Python :: 3
